kojen/Generate.py
kojen/Install.py
kojen/Language.py
kojen/LanguageCPP.py
kojen/LanguageCsharp.py
kojen/LanguagePython.py
kojen/__init__.py
kojen/__main__.py
kojen/cgen.py
kojen/coggen.py
kojen/kojentypes.py
kojen/plant.py
kojen/preservative.py
kojen/protogen.py
kojen/smgen.py
kojen/smvppxml.py
kojen/umlgen.py
kojen/vppclassdiagram.py
kojen/vppfs.py
kojen/allplatforms/CPP/CMakeLists.txt
kojen/allplatforms/CPP/Fault.cpp
kojen/allplatforms/CPP/Fault.h
kojen/allplatforms/CPP/IConnection.cpp
kojen/allplatforms/CPP/IConnection.h
kojen/allplatforms/CPP/IMsgReceiver.h
kojen/allplatforms/CPP/IRawDataReceiver.h
kojen/allplatforms/CPP/MsgHeader.h
kojen/allplatforms/CPP/allocator.cpp
kojen/allplatforms/CPP/allocator.h
kojen/allplatforms/CPP/basetypes.h
kojen/allplatforms/CPP/hooks_FreeRTOS.c
kojen/allplatforms/CPP/network.cpp
kojen/allplatforms/CPP/network.h
kojen/allplatforms/CPP/serialport.cpp
kojen/allplatforms/CPP/serialport.h
kojen/allplatforms/CPP/stl_allocator.h
kojen/allplatforms/CPP/tcpipclientserver.cpp
kojen/allplatforms/CPP/tcpipclientserver.h
kojen/allplatforms/CPP/thread_FreeRTOS.cpp
kojen/allplatforms/CPP/thread_FreeRTOS.h
kojen/allplatforms/CPP/threaded_dispatcher.h
kojen/allplatforms/CPP/threaded_dispatcher_FreeRTOS.h
kojen/allplatforms/CPP/threadsafe_queue.h
kojen/allplatforms/CPP/threadsafe_queue_FreeRTOS.h
kojen/allplatforms/CPP/waitcondition.cpp
kojen/allplatforms/CPP/waitcondition.h
kojen/allplatforms/CPP/xallocator.cpp
kojen/allplatforms/CPP/xallocator.h
kojen/allplatforms/CPP/xlist.h
kojen/allplatforms/CPP/xmap.h
kojen/allplatforms/CPP/xqueue.h
kojen/allplatforms/CPP/xset.h
kojen/allplatforms/CPP/xsstream.h
kojen/allplatforms/CPP/xstring.h
kojen/allplatforms/CPP/testsuite/CMakeLists.txt
kojen/allplatforms/CPP/testsuite/Test.IConnection.cpp
kojen/allplatforms/CPP/testsuite/Test.ThreadingConcepts.cpp
kojen/allplatforms/CPP/testsuite/test_main.cpp
kojen/classdiagram_templates/C#/ClassTemplate.cs
kojen/classdiagram_templates/C#/EnumTemplate.cs
kojen-1.4.59.dist-info/LICENSE
kojen-1.4.59.dist-info/METADATA
kojen-1.4.59.dist-info/WHEEL
kojen-1.4.59.dist-info/top_level.txt
kojen-1.4.59.dist-info/RECORD
