Metadata-Version: 2.1
Name: kojen
Version: 1.4.59
Summary: Code generation tools.
Home-page: https://github.com/kohjaen/kojen
Author: kohjaen
Author-email: koh.jaen@yahoo.de
Classifier: Programming Language :: Python :: 3
Classifier: License :: OSI Approved :: MIT License
Classifier: Operating System :: OS Independent
Requires-Python: >=3.6.8
License-File: LICENSE
Requires-Dist: cogapp>=3.0.0
